mtm/__init__.py
mtm/detection.py
mtm/nms.py
mtm-1.0.0.dist-info/LICENSE
mtm-1.0.0.dist-info/METADATA
mtm-1.0.0.dist-info/WHEEL
mtm-1.0.0.dist-info/top_level.txt
mtm-1.0.0.dist-info/RECORD
