Metadata-Version: 2.1
Name: mtm
Version: 1.0.0
Summary: Object-recognition in images using multiple templates (object-oriented implementation).
Home-page: https://github.com/multi-template-matching/mtm-python-oop
Author: Laurent Thomas
Author-email: laurent132.thomas@laposte.net
License: UNKNOWN
Project-URL: Bug Tracker, https://github.com/multi-template-matching/mtm-python-oop/issues
Platform: UNKNOWN
Classifier: Programming Language :: Python :: 3
Classifier: License :: OSI Approved :: MIT License
Classifier: Operating System :: OS Independent
Classifier: Topic :: Scientific/Engineering :: Image Recognition
Classifier: Intended Audience :: Science/Research
Requires-Python: >=3
License-File: LICENSE
Requires-Dist: numpy
Requires-Dist: scikit-image
Requires-Dist: shapely
Requires-Dist: matplotlib
